textBotPlus/__init__.py
textBotPlus/utils.py
textBotPlus-0.1.4.dist-info/LICENSE
textBotPlus-0.1.4.dist-info/METADATA
textBotPlus-0.1.4.dist-info/WHEEL
textBotPlus-0.1.4.dist-info/top_level.txt
textBotPlus-0.1.4.dist-info/RECORD
