Metadata-Version: 2.1
Name: textBotPlus
Version: 0.1.4
Summary: A Python package for text manipulation
Author: Ramesh Chandra
Author-email: rameshsofter@gmail.com
Classifier: Programming Language :: Python :: 3
Classifier: License :: OSI Approved :: MIT License
Classifier: Operating System :: OS Independent
Requires-Python: >=3.6
License-File: LICENSE
Requires-Dist: pandas==2.0.2
Requires-Dist: beautifulsoup4==4.12.2
